rtsp_network_scanner-2.5.4.dist-info/licenses/LICENSE
rtsp_scanner/__init__.py
rtsp_scanner/cli.py
rtsp_scanner/cli.py.backup
rtsp_scanner/core/__init__.py
rtsp_scanner/core/camera_checker.py
rtsp_scanner/core/channel_scanner.py
rtsp_scanner/core/port_scanner.py
rtsp_scanner/core/rtsp_tester.py
rtsp_scanner/tests/__init__.py
rtsp_scanner/utils/__init__.py
rtsp_scanner/utils/logger.py
rtsp_scanner/utils/network.py
rtsp_scanner/utils/output.py
rtsp_network_scanner-2.5.4.dist-info/METADATA
rtsp_network_scanner-2.5.4.dist-info/WHEEL
rtsp_network_scanner-2.5.4.dist-info/entry_points.txt
rtsp_network_scanner-2.5.4.dist-info/top_level.txt
rtsp_network_scanner-2.5.4.dist-info/RECORD
