Metadata-Version: 2.4
Name: rtsp-network-scanner
Version: 2.5.4
Summary: Scan networks for RTSP cameras, test streams, discover channels
Home-page: https://github.com/sssanjaya/rtsp-network-scanner
Author: Sanjay H
Author-email: Sanjay H <contact@sanjayhona.com.np>
License: MIT
Project-URL: Homepage, https://github.com/sssanjaya/rtsp-network-scanner
Project-URL: Bug Reports, https://github.com/sssanjaya/rtsp-network-scanner/issues
Project-URL: Source, https://github.com/sssanjaya/rtsp-network-scanner
Keywords: rtsp,scanner,network,camera,security,debug
Classifier: Development Status :: 4 - Beta
Classifier: Intended Audience :: Developers
Classifier: Intended Audience :: System Administrators
Classifier: Topic :: System :: Networking
Classifier: Topic :: Multimedia :: Video
Classifier: License :: OSI Approved :: MIT License
Classifier: Programming Language :: Python :: 3
Classifier: Programming Language :: Python :: 3.7
Classifier: Programming Language :: Python :: 3.8
Classifier: Programming Language :: Python :: 3.9
Classifier: Programming Language :: Python :: 3.10
Classifier: Programming Language :: Python :: 3.11
Requires-Python: >=3.7
License-File: LICENSE
Dynamic: author
Dynamic: home-page
Dynamic: license-file
Dynamic: requires-python
